config/__init__.py
config/config_manager.py
evaluator/__init__.py
evaluator/base_evaluator.py
evaluator/evaluator.py
evaluator/prompt_generator.py
evaluator/registry.py
evaluator/task_manager.py
lingualens-1.0.0.dist-info/licenses/LICENSE
models/__init__.py
models/anthropic.py
models/cloudverse.py
models/llm_manager.py
models/openai.py
pool/__init__.py
utils/llm_parser.py
utils/metrics.py
lingualens-1.0.0.dist-info/METADATA
lingualens-1.0.0.dist-info/WHEEL
lingualens-1.0.0.dist-info/top_level.txt
lingualens-1.0.0.dist-info/RECORD
